mplug/.pytest_cache/.gitignore
mplug/.pytest_cache/CACHEDIR.TAG
mplug/.pytest_cache/README.md
mplug/.pytest_cache/v/cache/nodeids
mplug/.pytest_cache/v/cache/stepwise
mplug/Session.vim
mplug/__init__.py
mplug/download.py
mplug/interaction.py
mplug/mplug.py
mplug/util.py
mplug-0.2.1.dist-info/entry_points.txt
mplug-0.2.1.dist-info/LICENSE
mplug-0.2.1.dist-info/WHEEL
mplug-0.2.1.dist-info/METADATA
mplug-0.2.1.dist-info/RECORD
