Metadata-Version: 2.1
Name: mplug
Version: 0.2.1
Summary: A plugin manager for mpv
Home-page: https://github.com/nudin/mplug
License: MPL-2.0
Keywords: mpv
Author: Michael F. Schönitzer
Author-email: michael@schoenitzer.de
Requires-Python: >=3.6,<4.0
Classifier: License :: OSI Approved
Classifier: Programming Language :: Python :: 3
Classifier: Programming Language :: Python :: 3.6
Classifier: Programming Language :: Python :: 3.7
Classifier: Programming Language :: Python :: 3.8
Requires-Dist: GitPython (>=3.1.7,<4.0.0)
Requires-Dist: importlib_metadata (>=1.7.0,<2.0.0); python_version < "3.8"
Requires-Dist: requests (>=2.24.0,<3.0.0)
Project-URL: Repository, https://github.com/nudin/mplug
